jimuflow/__init__.py
jimuflow/rc_icons.py
jimuflow/resource.py
jimuflow/version_info.py
jimuflow/common/__init__.py
jimuflow/common/fs.py
jimuflow/common/keyboard.py
jimuflow/common/mimetypes.py
jimuflow/common/uri_utils.py
jimuflow/common/web_element_utils.py
jimuflow/common/win32_functions.py
jimuflow/components/__init__.py
jimuflow/components/core/__init__.py
jimuflow/components/core/add_prefix_or_suffix_component.py
jimuflow/components/core/break_component.py
jimuflow/components/core/change_text_case_component.py
jimuflow/components/core/check_process_component.py
jimuflow/components/core/clear_folder_component.py
jimuflow/components/core/compress_file_component.py
jimuflow/components/core/condition_utils.py
jimuflow/components/core/continue_component.py
jimuflow/components/core/copy_file_component.py
jimuflow/components/core/copy_folder_component.py
jimuflow/components/core/create_date_component.py
jimuflow/components/core/create_date_time_component.py
jimuflow/components/core/create_dict_component.py
jimuflow/components/core/create_folder_component.py
jimuflow/components/core/create_list_component.py
jimuflow/components/core/create_time_component.py
jimuflow/components/core/datetime_utils.py
jimuflow/components/core/decompress_file_component.py
jimuflow/components/core/delete_dict_key_component.py
jimuflow/components/core/delete_file_component.py
jimuflow/components/core/delete_folder_component.py
jimuflow/components/core/delete_list_item_component.py
jimuflow/components/core/dict_loop_component.py
jimuflow/components/core/diff_date_time_component.py
jimuflow/components/core/else_component.py
jimuflow/components/core/else_if_component.py
jimuflow/components/core/else_if_conditions_component.py
jimuflow/components/core/execute_cmd_component.py
jimuflow/components/core/exit_component.py
jimuflow/components/core/format_date_time_component.py
jimuflow/components/core/get_clipboard_text_component.py
jimuflow/components/core/get_file_path_info_component.py
jimuflow-1.0.6.dist-info/licenses/LICENSE
jimuflow-1.0.6.dist-info/METADATA
jimuflow-1.0.6.dist-info/WHEEL
jimuflow-1.0.6.dist-info/entry_points.txt
jimuflow-1.0.6.dist-info/top_level.txt
jimuflow-1.0.6.dist-info/RECORD
