Metadata-Version: 2.4
Name: jimuflow
Version: 1.0.6
Summary: A simple and easy-to-use cross-platform RPA tool
Author-email: Weng Jing <superwhisper@hotmail.com>
License:                     GNU GENERAL PUBLIC LICENSE
Project-URL: Homepage, https://github.com/jimuflow/jimuflow
Project-URL: Repository, https://github.com/jimuflow/jimuflow
Classifier: License :: OSI Approved :: GNU General Public License v3 (GPLv3)
Classifier: Programming Language :: Python :: 3
Classifier: Operating System :: OS Independent
Requires-Python: <3.14,>=3.12
License-File: LICENSE
Requires-Dist: PySide6>=6.8.1.1
Requires-Dist: lark
Requires-Dist: playwright
Requires-Dist: openpyxl
Requires-Dist: xlrd
Requires-Dist: xlwt
Requires-Dist: python-dateutil
Requires-Dist: pyperclip
Requires-Dist: psutil
Requires-Dist: Babel
Requires-Dist: arrow
Requires-Dist: pyautogui
Requires-Dist: opencv-python
Requires-Dist: pywinauto
Requires-Dist: lxml
Requires-Dist: pillow
Requires-Dist: requests
Requires-Dist: requests[socks]
Requires-Dist: mysql-connector-python
Requires-Dist: psycopg2-binary
Requires-Dist: pymssql
Provides-Extra: dev
Requires-Dist: pytest; extra == "dev"
Requires-Dist: pytest-asyncio; extra == "dev"
Requires-Dist: freezegun; extra == "dev"
Requires-Dist: pyinstaller; extra == "dev"
Requires-Dist: tomli; extra == "dev"
Requires-Dist: pytest-httpbin; extra == "dev"
Provides-Extra: docs
Requires-Dist: mkdocs; extra == "docs"
Requires-Dist: mkdocs[i18n]; extra == "docs"
Provides-Extra: all
Requires-Dist: pytest; extra == "all"
Requires-Dist: pytest-asyncio; extra == "all"
Requires-Dist: freezegun; extra == "all"
Requires-Dist: pyinstaller; extra == "all"
Requires-Dist: tomli; extra == "all"
Requires-Dist: pytest-httpbin; extra == "all"
Requires-Dist: mkdocs; extra == "all"
Requires-Dist: mkdocs[i18n]; extra == "all"
Dynamic: license-file
